azext_imagecopy/__init__.py
azext_imagecopy/_help.py
azext_imagecopy/azext_metadata.json
azext_imagecopy/cli_utils.py
azext_imagecopy/create_target.py
azext_imagecopy/custom.py
image_copy_extension-0.2.4.dist-info/DESCRIPTION.rst
image_copy_extension-0.2.4.dist-info/METADATA
image_copy_extension-0.2.4.dist-info/RECORD
image_copy_extension-0.2.4.dist-info/WHEEL
image_copy_extension-0.2.4.dist-info/metadata.json
image_copy_extension-0.2.4.dist-info/top_level.txt
