Metadata-Version: 2.0
Name: image-copy-extension
Version: 0.2.4
Summary: Support for copying managed vm images between regions
Home-page: https://github.com/Azure/azure-cli-extensions
Author: Tamir Kamara
Author-email: tamir.kamara@microsoft.com
License: MIT
Platform: UNKNOWN
Classifier: Development Status :: 4 - Beta
Classifier: Intended Audience :: Developers
Classifier: Intended Audience :: System Administrators
Classifier: Programming Language :: Python
Classifier: Programming Language :: Python :: 2
Classifier: Programming Language :: Python :: 2.7
Classifier: Programming Language :: Python :: 3
Classifier: Programming Language :: Python :: 3.4
Classifier: Programming Language :: Python :: 3.5
Classifier: Programming Language :: Python :: 3.6
Classifier: License :: OSI Approved :: MIT License
